notmuchtask/__init__.py
notmuchtask/sync.py
notmuchtask/cli/__init__.py
notmuchtask/cli/commands.py
notmuchtask/cli/config.py
notmuchtask/cli/exitcodes.py
notmuchtask/cli/globals.py
notmuchtask/cli/main.py
notmuchtask/messages/__init__.py
notmuchtask/messages/charset_decoder.py
notmuchtask/messages/eml_parser.py
notmuchtask/messages/extract.py
notmuchtask/messages/mail.py
notmuchtask/messages/message.py
notmuchtask/messages/repository.py
notmuchtask/tasks/__init__.py
notmuchtask/tasks/repository.py
notmuchtask-0.0.3.dist-info/LICENSE.md
notmuchtask-0.0.3.dist-info/LICENSE.notmuch
notmuchtask-0.0.3.dist-info/METADATA
notmuchtask-0.0.3.dist-info/WHEEL
notmuchtask-0.0.3.dist-info/entry_points.txt
notmuchtask-0.0.3.dist-info/top_level.txt
notmuchtask-0.0.3.dist-info/RECORD
