Metadata-Version: 2.1
Name: notmuchtask
Version: 0.0.3
Summary: Sync mails in notmuch with taskwarrior
Home-page: https://github.com/neuhalje/notmuch-task
Author: Jens Neuhalfen
Author-email: jens@neuhalfen.name
License: MIT
Platform: UNKNOWN
Classifier: Development Status :: 1 - Planning
Classifier: Natural Language :: English
Classifier: Operating System :: OS Independent
Classifier: Programming Language :: Python
Classifier: Programming Language :: Python :: 3
Classifier: Programming Language :: Python :: 3.6
Requires-Python: >=3.5
Requires-Dist: click (<7.1,>=7.0)
Requires-Dist: html2text (>=2018.1.9)
Requires-Dist: notmuch
